{
  "VIX": {
    "price": 21.51,
    "change": 33.94,
    "time": "2026-06-05T22:52:35.413541"
  },
  "DXY": {
    "price": 100.07,
    "change": 0.66,
    "time": "2026-06-05T22:52:35.478315"
  },
  "TLT": {
    "price": 85.06,
    "change": -0.51,
    "time": "2026-06-05T22:52:35.574752"
  },
  "TNX": {
    "price": 4.54,
    "change": 1.32,
    "time": "2026-06-05T22:52:35.633959"
  },
  "SPY": {
    "price": 737.55,
    "change": -2.58,
    "time": "2026-06-05T22:52:35.752512"
  },
  "XLK": {
    "price": 180.3,
    "change": 0.0,
    "time": "2026-06-05T22:52:35.822589"
  },
  "ARKK": {
    "price": 74.49,
    "change": 0.0,
    "time": "2026-06-05T22:52:35.891230"
  },
  "ARKF": {
    "price": 38.18,
    "change": 0.0,
    "time": "2026-06-05T22:52:35.956572"
  },
  "WCLD": {
    "price": 32.2,
    "change": 0.0,
    "time": "2026-06-05T22:52:36.023978"
  },
  "ROBT": {
    "price": 55.56,
    "change": 0.0,
    "time": "2026-06-05T22:52:36.097013"
  },
  "MU": {
    "price": 864.01,
    "change": 0.0,
    "time": "2026-06-05T22:52:36.166395"
  },
  "ARKG": {
    "price": 33.41,
    "change": 0.0,
    "time": "2026-06-05T22:52:36.235371"
  },
  "IGV": {
    "price": 95.85,
    "change": 0.0,
    "time": "2026-06-05T22:52:36.312822"
  }
}